odoo/addons/event_registration_qr_code/README.rst
odoo/addons/event_registration_qr_code/__init__.py
odoo/addons/event_registration_qr_code/__manifest__.py
odoo/addons/event_registration_qr_code/i18n/ca.po
odoo/addons/event_registration_qr_code/i18n/de.po
odoo/addons/event_registration_qr_code/i18n/es.po
odoo/addons/event_registration_qr_code/i18n/event_registration_qr_code.pot
odoo/addons/event_registration_qr_code/i18n/fr_FR.po
odoo/addons/event_registration_qr_code/i18n/it.po
odoo/addons/event_registration_qr_code/models/__init__.py
odoo/addons/event_registration_qr_code/models/event_registration.py
odoo/addons/event_registration_qr_code/readme/CONTRIBUTORS.rst
odoo/addons/event_registration_qr_code/readme/DESCRIPTION.rst
odoo/addons/event_registration_qr_code/reports/report_templates.xml
odoo/addons/event_registration_qr_code/static/description/icon.png
odoo/addons/event_registration_qr_code/static/description/index.html
odoo/addons/event_registration_qr_code/tests/__init__.py
odoo/addons/event_registration_qr_code/tests/test_event_registration_qr_code.py
odoo/addons/event_registration_qr_code/views/event_registration.xml
odoo_addon_event_registration_qr_code-16.0.1.0.0.5.dist-info/METADATA
odoo_addon_event_registration_qr_code-16.0.1.0.0.5.dist-info/WHEEL
odoo_addon_event_registration_qr_code-16.0.1.0.0.5.dist-info/top_level.txt
odoo_addon_event_registration_qr_code-16.0.1.0.0.5.dist-info/RECORD
